symphony_scatterplot/__init__.py
symphony_scatterplot/_frontend.py
symphony_scatterplot/_version.py
symphony_scatterplot/widget.py
symphony_scatterplot/labextension/build_log.json
symphony_scatterplot/labextension/package.json
symphony_scatterplot/labextension/static/lib_index_js.1b06b8ab55df36e1be1b.js
symphony_scatterplot/labextension/static/lib_index_js.1b06b8ab55df36e1be1b.js.map
symphony_scatterplot/labextension/static/lib_index_js.348f0931371848a6c821.js
symphony_scatterplot/labextension/static/lib_index_js.348f0931371848a6c821.js.map
symphony_scatterplot/labextension/static/remoteEntry.d03c6065b69d93d4e7f8.js
symphony_scatterplot/labextension/static/remoteEntry.d03c6065b69d93d4e7f8.js.map
symphony_scatterplot/labextension/static/remoteEntry.f2950ae78a374ac7bf59.js
symphony_scatterplot/labextension/static/remoteEntry.f2950ae78a374ac7bf59.js.map
symphony_scatterplot/labextension/static/style.js
symphony_scatterplot/nbextension/extension.js
symphony_scatterplot/nbextension/index.js
symphony_scatterplot/standalone/widgets/SymphonyScatterplot.js
symphony_scatterplot/standalone/widgets/SymphonyScatterplot.js.map
symphony_scatterplot-1.0.2.data/data/etc/jupyter/nbconfig/notebook.d/symphony_scatterplot.json
symphony_scatterplot-1.0.2.data/data/share/jupyter/labextensions/symphony-scatterplot/build_log.json
symphony_scatterplot-1.0.2.data/data/share/jupyter/labextensions/symphony-scatterplot/install.json
symphony_scatterplot-1.0.2.data/data/share/jupyter/labextensions/symphony-scatterplot/package.json
symphony_scatterplot-1.0.2.data/data/share/jupyter/labextensions/symphony-scatterplot/static/lib_index_js.348f0931371848a6c821.js
symphony_scatterplot-1.0.2.data/data/share/jupyter/labextensions/symphony-scatterplot/static/lib_index_js.348f0931371848a6c821.js.map
symphony_scatterplot-1.0.2.data/data/share/jupyter/labextensions/symphony-scatterplot/static/remoteEntry.f2950ae78a374ac7bf59.js
symphony_scatterplot-1.0.2.dist-info/LICENSE.txt
symphony_scatterplot-1.0.2.dist-info/METADATA
symphony_scatterplot-1.0.2.dist-info/WHEEL
symphony_scatterplot-1.0.2.dist-info/top_level.txt
symphony_scatterplot-1.0.2.dist-info/RECORD
